app_rappi_dfmejial/__init__.py
app_rappi_dfmejial/conf/settings.py
app_rappi_dfmejial/data/__init__.py
app_rappi_dfmejial/data/pre_processer.py
app_rappi_dfmejial/data/raw_data/test.csv
app_rappi_dfmejial/data/raw_data/train.csv
app_rappi_dfmejial/data/reader.py
app_rappi_dfmejial/main.py
app_rappi_dfmejial/model/train.py
app_rappi_dfmejial/notebooks/d.ipynb
app_rappi_dfmejial/tests/__init__.py
app_rappi_dfmejial/tests/data/test_pre_processer.py
app_rappi_dfmejial/tests/data/test_reader.py
app_rappi_dfmejial/tests/model/test_train.py
app_rappi_dfmejial/tests/test_main.py
app_rappi_dfmejial-0.0.5.dist-info/entry_points.txt
app_rappi_dfmejial-0.0.5.dist-info/LICENSE
app_rappi_dfmejial-0.0.5.dist-info/WHEEL
app_rappi_dfmejial-0.0.5.dist-info/METADATA
app_rappi_dfmejial-0.0.5.dist-info/RECORD
